LICENSE
MANIFEST.in
README.md
setup.cfg
setup.py
btyper3/__init__.py
btyper3/__main__.py
btyper3/ani.py
btyper3/blast.py
btyper3/mlst.py
btyper3/print_final_results.py
btyper3.egg-info/PKG-INFO
btyper3.egg-info/SOURCES.txt
btyper3.egg-info/dependency_links.txt
btyper3.egg-info/entry_points.txt
btyper3.egg-info/not-zip-safe
btyper3.egg-info/requires.txt
btyper3.egg-info/top_level.txt
btyper3/seq_ani_db/__init__.py
btyper3/seq_ani_db/geneflow/__init__.py
btyper3/seq_ani_db/geneflow/geneflow.tsv
btyper3/seq_ani_db/species/__init__.py
btyper3/seq_ani_db/species/species.tsv
btyper3/seq_ani_db/subspecies/__init__.py
btyper3/seq_ani_db/subspecies/subspecies.tsv
btyper3/seq_ani_db/typestrains/__init__.py
btyper3/seq_ani_db/typestrains/typestrains.tsv
btyper3/seq_bt_db/__init__.py
btyper3/seq_bt_db/btyper3_bt_sequences.faa
btyper3/seq_mlst_db/__init__.py
btyper3/seq_mlst_db/pubmlst.xml
btyper3/seq_panC_db/__init__.py
btyper3/seq_panC_db/panC.fna
btyper3/seq_virulence_db/__init__.py
btyper3/seq_virulence_db/btyper3_virulence_sequences.faa
btyper3/seq_virulence_db/btyper3_virulence_sequences.ffn