Metadata-Version: 2.1
Name: btyper3
Version: 3.3.4
Summary: In silico taxonomic classification of Bacillus cereus group isolates using assembled genomes
Home-page: https://github.com/lmc297/btyper3
Author: Laura M. Carroll
Author-email: lmc297@cornell.edu
License: GPLv3
Project-URL: Bug Tracker, https://github.com/lmc297/btyper3/issues
Project-URL: Publication, https://www.ncbi.nlm.nih.gov/pmc/articles/PMC7536271/
Project-URL: Changelog, https://github.com/lmc297/btyper3/blob/master/archive/CHANGELOG.md
Keywords: bacillus,taxonomy,genome,ANI
Platform: any
Classifier: Development Status :: 6 - Mature
Classifier: Intended Audience :: Science/Research
Classifier: License :: OSI Approved :: GNU General Public License v3 (GPLv3)
Classifier: Operating System :: OS Independent
Classifier: Programming Language :: Python
Classifier: Programming Language :: Python :: 3
Classifier: Topic :: Scientific/Engineering :: Bio-Informatics
Requires-Python: >=3.7
License-File: LICENSE
